oracledb/__init__.py
oracledb/aq.py
oracledb/base_impl.cpython-39-x86_64-linux-gnu.so
oracledb/connect_params.py
oracledb/connection.py
oracledb/constants.py
oracledb/constructors.py
oracledb/cursor.py
oracledb/dbobject.py
oracledb/defaults.py
oracledb/driver_mode.py
oracledb/dsn.py
oracledb/errors.py
oracledb/exceptions.py
oracledb/lob.py
oracledb/pool.py
oracledb/pool_params.py
oracledb/py.typed
oracledb/soda.py
oracledb/subscr.py
oracledb/thick_impl.cpython-39-x86_64-linux-gnu.so
oracledb/thin_impl.cpython-39-x86_64-linux-gnu.so
oracledb/utils.py
oracledb/var.py
oracledb/version.py
oracledb_glue-1.3.0b1.dist-info/LICENSE.txt
oracledb_glue-1.3.0b1.dist-info/METADATA
oracledb_glue-1.3.0b1.dist-info/NOTICE.txt
oracledb_glue-1.3.0b1.dist-info/THIRD_PARTY_LICENSES.txt
oracledb_glue-1.3.0b1.dist-info/WHEEL
oracledb_glue-1.3.0b1.dist-info/top_level.txt
oracledb_glue-1.3.0b1.dist-info/RECORD
