Metadata-Version: 2.1
Name: oracledb-glue
Version: 1.3.0b1
Summary: Python interface to Oracle Database
Home-page: https://oracle.github.io/python-oracledb
Author: Anthony Tuininga
Author-email: anthony.tuininga@oracle.com
License: Apache and/or UPL
Project-URL: Installation, https://python-oracledb.readthedocs.io/en/latest/user_guide/installation.html
Project-URL: Samples, https://github.com/oracle/python-oracledb/tree/main/samples
Project-URL: Documentation, http://python-oracledb.readthedocs.io
Project-URL: Release Notes, https://python-oracledb.readthedocs.io/en/latest/release_notes.html#releasenotes
Project-URL: Issues, https://github.com/oracle/python-oracledb/issues
Project-URL: Source, https://github.com/oracle/python-oracledb
Keywords: Oracle,database
Classifier: Development Status :: 5 - Production/Stable
Classifier: Intended Audience :: Developers
Classifier: License :: OSI Approved :: Universal Permissive License (UPL)
Classifier: License :: OSI Approved :: Apache Software License
Classifier: Natural Language :: English
Classifier: Operating System :: OS Independent
Classifier: Programming Language :: Python :: 3 :: Only
Classifier: Programming Language :: Python :: Implementation :: CPython
Classifier: Programming Language :: Cython
Classifier: Topic :: Database
Requires-Python: >=3.6
License-File: LICENSE.txt
License-File: THIRD_PARTY_LICENSES.txt
License-File: NOTICE.txt
Requires-Dist: cryptography (>=3.2.1)
